{
  "updated_at": "2026-07-19T21:39:46+00:00",
  "slate_date": "2026-07-19",
  "source": "The Odds API",
  "sportsbooks": [
    "draftkings",
    "fanduel"
  ],
  "market": "player_points",
  "props": [
    {
      "player": "Allisha Gray",
      "market": "pts",
      "market_label": "Points",
      "line": 26.5,
      "bookmaker": "draftkings",
      "bookmaker_label": "DraftKings",
      "event_id": "816ff571af3364f94a70ee7d377cff0d",
      "commence_time": "2026-07-19T20:15:00Z",
      "home_team_name": "Atlanta Dream",
      "away_team_name": "Chicago Sky"
    },
    {
      "player": "Allisha Gray",
      "market": "pts",
      "market_label": "Points",
      "line": 26.5,
      "bookmaker": "fanduel",
      "bookmaker_label": "FanDuel",
      "event_id": "816ff571af3364f94a70ee7d377cff0d",
      "commence_time": "2026-07-19T20:15:00Z",
      "home_team_name": "Atlanta Dream",
      "away_team_name": "Chicago Sky"
    },
    {
      "player": "Angel Reese",
      "market": "pts",
      "market_label": "Points",
      "line": 11.5,
      "bookmaker": "draftkings",
      "bookmaker_label": "DraftKings",
      "event_id": "816ff571af3364f94a70ee7d377cff0d",
      "commence_time": "2026-07-19T20:15:00Z",
      "home_team_name": "Atlanta Dream",
      "away_team_name": "Chicago Sky"
    },
    {
      "player": "Angel Reese",
      "market": "pts",
      "market_label": "Points",
      "line": 11.5,
      "bookmaker": "fanduel",
      "bookmaker_label": "FanDuel",
      "event_id": "816ff571af3364f94a70ee7d377cff0d",
      "commence_time": "2026-07-19T20:15:00Z",
      "home_team_name": "Atlanta Dream",
      "away_team_name": "Chicago Sky"
    },
    {
      "player": "Azura Stevens",
      "market": "pts",
      "market_label": "Points",
      "line": 15.5,
      "bookmaker": "draftkings",
      "bookmaker_label": "DraftKings",
      "event_id": "816ff571af3364f94a70ee7d377cff0d",
      "commence_time": "2026-07-19T20:15:00Z",
      "home_team_name": "Atlanta Dream",
      "away_team_name": "Chicago Sky"
    },
    {
      "player": "Azura Stevens",
      "market": "pts",
      "market_label": "Points",
      "line": 16.5,
      "bookmaker": "fanduel",
      "bookmaker_label": "FanDuel",
      "event_id": "816ff571af3364f94a70ee7d377cff0d",
      "commence_time": "2026-07-19T20:15:00Z",
      "home_team_name": "Atlanta Dream",
      "away_team_name": "Chicago Sky"
    },
    {
      "player": "Kamilla Cardoso",
      "market": "pts",
      "market_label": "Points",
      "line": 13.5,
      "bookmaker": "draftkings",
      "bookmaker_label": "DraftKings",
      "event_id": "816ff571af3364f94a70ee7d377cff0d",
      "commence_time": "2026-07-19T20:15:00Z",
      "home_team_name": "Atlanta Dream",
      "away_team_name": "Chicago Sky"
    },
    {
      "player": "Kamilla Cardoso",
      "market": "pts",
      "market_label": "Points",
      "line": 13.5,
      "bookmaker": "fanduel",
      "bookmaker_label": "FanDuel",
      "event_id": "816ff571af3364f94a70ee7d377cff0d",
      "commence_time": "2026-07-19T20:15:00Z",
      "home_team_name": "Atlanta Dream",
      "away_team_name": "Chicago Sky"
    },
    {
      "player": "Natasha Cloud",
      "market": "pts",
      "market_label": "Points",
      "line": 7.5,
      "bookmaker": "draftkings",
      "bookmaker_label": "DraftKings",
      "event_id": "816ff571af3364f94a70ee7d377cff0d",
      "commence_time": "2026-07-19T20:15:00Z",
      "home_team_name": "Atlanta Dream",
      "away_team_name": "Chicago Sky"
    },
    {
      "player": "Natasha Cloud",
      "market": "pts",
      "market_label": "Points",
      "line": 7.5,
      "bookmaker": "fanduel",
      "bookmaker_label": "FanDuel",
      "event_id": "816ff571af3364f94a70ee7d377cff0d",
      "commence_time": "2026-07-19T20:15:00Z",
      "home_team_name": "Atlanta Dream",
      "away_team_name": "Chicago Sky"
    },
    {
      "player": "Rhyne Howard",
      "market": "pts",
      "market_label": "Points",
      "line": 14.5,
      "bookmaker": "draftkings",
      "bookmaker_label": "DraftKings",
      "event_id": "816ff571af3364f94a70ee7d377cff0d",
      "commence_time": "2026-07-19T20:15:00Z",
      "home_team_name": "Atlanta Dream",
      "away_team_name": "Chicago Sky"
    },
    {
      "player": "Rhyne Howard",
      "market": "pts",
      "market_label": "Points",
      "line": 14.5,
      "bookmaker": "fanduel",
      "bookmaker_label": "FanDuel",
      "event_id": "816ff571af3364f94a70ee7d377cff0d",
      "commence_time": "2026-07-19T20:15:00Z",
      "home_team_name": "Atlanta Dream",
      "away_team_name": "Chicago Sky"
    },
    {
      "player": "Sydney Taylor",
      "market": "pts",
      "market_label": "Points",
      "line": 14.5,
      "bookmaker": "draftkings",
      "bookmaker_label": "DraftKings",
      "event_id": "816ff571af3364f94a70ee7d377cff0d",
      "commence_time": "2026-07-19T20:15:00Z",
      "home_team_name": "Atlanta Dream",
      "away_team_name": "Chicago Sky"
    },
    {
      "player": "Sydney Taylor",
      "market": "pts",
      "market_label": "Points",
      "line": 14.5,
      "bookmaker": "fanduel",
      "bookmaker_label": "FanDuel",
      "event_id": "816ff571af3364f94a70ee7d377cff0d",
      "commence_time": "2026-07-19T20:15:00Z",
      "home_team_name": "Atlanta Dream",
      "away_team_name": "Chicago Sky"
    },
    {
      "player": "Aaliyah Edwards",
      "market": "pts",
      "market_label": "Points",
      "line": 11.5,
      "bookmaker": "draftkings",
      "bookmaker_label": "DraftKings",
      "event_id": "fc804cb9450e1bdff88768da90a4a79d",
      "commence_time": "2026-07-19T23:00:00Z",
      "home_team_name": "Phoenix Mercury",
      "away_team_name": "Connecticut Sun"
    },
    {
      "player": "Alyssa Thomas",
      "market": "pts",
      "market_label": "Points",
      "line": 13.5,
      "bookmaker": "draftkings",
      "bookmaker_label": "DraftKings",
      "event_id": "fc804cb9450e1bdff88768da90a4a79d",
      "commence_time": "2026-07-19T23:00:00Z",
      "home_team_name": "Phoenix Mercury",
      "away_team_name": "Connecticut Sun"
    },
    {
      "player": "Alyssa Thomas",
      "market": "pts",
      "market_label": "Points",
      "line": 13.5,
      "bookmaker": "fanduel",
      "bookmaker_label": "FanDuel",
      "event_id": "fc804cb9450e1bdff88768da90a4a79d",
      "commence_time": "2026-07-19T23:00:00Z",
      "home_team_name": "Phoenix Mercury",
      "away_team_name": "Connecticut Sun"
    },
    {
      "player": "Brittney Griner",
      "market": "pts",
      "market_label": "Points",
      "line": 12.5,
      "bookmaker": "draftkings",
      "bookmaker_label": "DraftKings",
      "event_id": "fc804cb9450e1bdff88768da90a4a79d",
      "commence_time": "2026-07-19T23:00:00Z",
      "home_team_name": "Phoenix Mercury",
      "away_team_name": "Connecticut Sun"
    },
    {
      "player": "Brittney Griner",
      "market": "pts",
      "market_label": "Points",
      "line": 12.5,
      "bookmaker": "fanduel",
      "bookmaker_label": "FanDuel",
      "event_id": "fc804cb9450e1bdff88768da90a4a79d",
      "commence_time": "2026-07-19T23:00:00Z",
      "home_team_name": "Phoenix Mercury",
      "away_team_name": "Connecticut Sun"
    },
    {
      "player": "Charlisse Leger-Walker",
      "market": "pts",
      "market_label": "Points",
      "line": 8.5,
      "bookmaker": "draftkings",
      "bookmaker_label": "DraftKings",
      "event_id": "fc804cb9450e1bdff88768da90a4a79d",
      "commence_time": "2026-07-19T23:00:00Z",
      "home_team_name": "Phoenix Mercury",
      "away_team_name": "Connecticut Sun"
    },
    {
      "player": "Charlisse Leger-Walker",
      "market": "pts",
      "market_label": "Points",
      "line": 7.5,
      "bookmaker": "fanduel",
      "bookmaker_label": "FanDuel",
      "event_id": "fc804cb9450e1bdff88768da90a4a79d",
      "commence_time": "2026-07-19T23:00:00Z",
      "home_team_name": "Phoenix Mercury",
      "away_team_name": "Connecticut Sun"
    },
    {
      "player": "DeWanna Bonner",
      "market": "pts",
      "market_label": "Points",
      "line": 9.5,
      "bookmaker": "draftkings",
      "bookmaker_label": "DraftKings",
      "event_id": "fc804cb9450e1bdff88768da90a4a79d",
      "commence_time": "2026-07-19T23:00:00Z",
      "home_team_name": "Phoenix Mercury",
      "away_team_name": "Connecticut Sun"
    },
    {
      "player": "DeWanna Bonner",
      "market": "pts",
      "market_label": "Points",
      "line": 9.5,
      "bookmaker": "fanduel",
      "bookmaker_label": "FanDuel",
      "event_id": "fc804cb9450e1bdff88768da90a4a79d",
      "commence_time": "2026-07-19T23:00:00Z",
      "home_team_name": "Phoenix Mercury",
      "away_team_name": "Connecticut Sun"
    },
    {
      "player": "Diamond Miller",
      "market": "pts",
      "market_label": "Points",
      "line": 9.5,
      "bookmaker": "draftkings",
      "bookmaker_label": "DraftKings",
      "event_id": "fc804cb9450e1bdff88768da90a4a79d",
      "commence_time": "2026-07-19T23:00:00Z",
      "home_team_name": "Phoenix Mercury",
      "away_team_name": "Connecticut Sun"
    },
    {
      "player": "Diamond Miller",
      "market": "pts",
      "market_label": "Points",
      "line": 8.5,
      "bookmaker": "fanduel",
      "bookmaker_label": "FanDuel",
      "event_id": "fc804cb9450e1bdff88768da90a4a79d",
      "commence_time": "2026-07-19T23:00:00Z",
      "home_team_name": "Phoenix Mercury",
      "away_team_name": "Connecticut Sun"
    },
    {
      "player": "Kahleah Copper",
      "market": "pts",
      "market_label": "Points",
      "line": 20.5,
      "bookmaker": "draftkings",
      "bookmaker_label": "DraftKings",
      "event_id": "fc804cb9450e1bdff88768da90a4a79d",
      "commence_time": "2026-07-19T23:00:00Z",
      "home_team_name": "Phoenix Mercury",
      "away_team_name": "Connecticut Sun"
    },
    {
      "player": "Kahleah Copper",
      "market": "pts",
      "market_label": "Points",
      "line": 21.5,
      "bookmaker": "fanduel",
      "bookmaker_label": "FanDuel",
      "event_id": "fc804cb9450e1bdff88768da90a4a79d",
      "commence_time": "2026-07-19T23:00:00Z",
      "home_team_name": "Phoenix Mercury",
      "away_team_name": "Connecticut Sun"
    },
    {
      "player": "Kennedy Burke",
      "market": "pts",
      "market_label": "Points",
      "line": 7.5,
      "bookmaker": "draftkings",
      "bookmaker_label": "DraftKings",
      "event_id": "fc804cb9450e1bdff88768da90a4a79d",
      "commence_time": "2026-07-19T23:00:00Z",
      "home_team_name": "Phoenix Mercury",
      "away_team_name": "Connecticut Sun"
    },
    {
      "player": "Le\u00efla Lacan",
      "market": "pts",
      "market_label": "Points",
      "line": 13.5,
      "bookmaker": "draftkings",
      "bookmaker_label": "DraftKings",
      "event_id": "fc804cb9450e1bdff88768da90a4a79d",
      "commence_time": "2026-07-19T23:00:00Z",
      "home_team_name": "Phoenix Mercury",
      "away_team_name": "Connecticut Sun"
    },
    {
      "player": "Le\u00efla Lacan",
      "market": "pts",
      "market_label": "Points",
      "line": 13.5,
      "bookmaker": "fanduel",
      "bookmaker_label": "FanDuel",
      "event_id": "fc804cb9450e1bdff88768da90a4a79d",
      "commence_time": "2026-07-19T23:00:00Z",
      "home_team_name": "Phoenix Mercury",
      "away_team_name": "Connecticut Sun"
    },
    {
      "player": "Monique Akoa Makani",
      "market": "pts",
      "market_label": "Points",
      "line": 9.5,
      "bookmaker": "draftkings",
      "bookmaker_label": "DraftKings",
      "event_id": "fc804cb9450e1bdff88768da90a4a79d",
      "commence_time": "2026-07-19T23:00:00Z",
      "home_team_name": "Phoenix Mercury",
      "away_team_name": "Connecticut Sun"
    },
    {
      "player": "Monique Akoa Makani",
      "market": "pts",
      "market_label": "Points",
      "line": 9.5,
      "bookmaker": "fanduel",
      "bookmaker_label": "FanDuel",
      "event_id": "fc804cb9450e1bdff88768da90a4a79d",
      "commence_time": "2026-07-19T23:00:00Z",
      "home_team_name": "Phoenix Mercury",
      "away_team_name": "Connecticut Sun"
    },
    {
      "player": "Natasha Mack",
      "market": "pts",
      "market_label": "Points",
      "line": 6.5,
      "bookmaker": "draftkings",
      "bookmaker_label": "DraftKings",
      "event_id": "fc804cb9450e1bdff88768da90a4a79d",
      "commence_time": "2026-07-19T23:00:00Z",
      "home_team_name": "Phoenix Mercury",
      "away_team_name": "Connecticut Sun"
    },
    {
      "player": "Olivia Nelson-Ododa",
      "market": "pts",
      "market_label": "Points",
      "line": 10.5,
      "bookmaker": "draftkings",
      "bookmaker_label": "DraftKings",
      "event_id": "fc804cb9450e1bdff88768da90a4a79d",
      "commence_time": "2026-07-19T23:00:00Z",
      "home_team_name": "Phoenix Mercury",
      "away_team_name": "Connecticut Sun"
    },
    {
      "player": "Olivia Nelson-Ododa",
      "market": "pts",
      "market_label": "Points",
      "line": 9.5,
      "bookmaker": "fanduel",
      "bookmaker_label": "FanDuel",
      "event_id": "fc804cb9450e1bdff88768da90a4a79d",
      "commence_time": "2026-07-19T23:00:00Z",
      "home_team_name": "Phoenix Mercury",
      "away_team_name": "Connecticut Sun"
    }
  ]
}